<?xml version='1.0' encoding='utf-8'?>
<news><id>32</id><url>http://www.cankaoxiaoxi.com/china/20201030/2423631.shtml</url><title>志愿军老战士程龙江：“炸坦克那一刻，我就没想活”</title><datetime>2020-10-30 8:07</datetime><body>参考消息网10月30日报道 （文/于也童）对程龙江老人的采访是从握手开始的。这是一双略显粗糙的手，也是一双有力、温暖、让人备感踏实的手。中国人民志愿军立功证明书、抗美援朝纪念勋章、残疾军人证……这双手慢慢打开一个塑料袋，拿出里面的“珍藏”，也慢慢打开了这名志愿军老战士一生难忘的戎马生涯。“我是共产党员，我不去谁去！”1948年，程龙江参军，先后参加辽沈战役、平津战役，一路从长白山打到海南岛。1950年，抗美援朝的战火燃起，10月19日，程龙江所在的中国人民志愿军第40军118师354团从鸭绿江出征，踏上了朝鲜战场。11月初，第二次战役爆发，第40军正面突击美军第2师。刚到朝鲜不久的程龙江经历了“人生中最困难的一次战役”。“美军的战术主要是飞机轰炸、炮轰，然后是坦克和步兵，轰炸的时候我们就藏在山洞里，但坦克上来后我们要是不阻拦，后面步兵就过来了。绝不能让坦克突破我们的防线。”程龙江回忆。如何阻拦坦克？“我思前想后只能用反坦克手雷近距离炸坏坦克，否则我们没有胜算。”程龙江说。</body></news>